itk/ITKAnisotropicSmoothingPython.py
itk/ITKAntiAliasPython.py
itk/ITKBiasCorrectionPython.py
itk/ITKBinaryMathematicalMorphologyPython.py
itk/ITKColormapPython.py
itk/ITKConnectedComponentsPython.py
itk/ITKDeconvolutionPython.py
itk/ITKDistanceMapPython.py
itk/ITKFastMarchingBasePython.py
itk/ITKFastMarchingPython.py
itk/ITKImageComparePython.py
itk/ITKImageFeaturePython.py
itk/ITKImageFrequencyPython.py
itk/ITKImageFusionPython.py
itk/ITKImageGradientPython.py
itk/ITKImageLabelPython.py
itk/ITKImageNoisePython.py
itk/ITKLabelMapBasePython.py
itk/ITKLabelMapPython.py
itk/ITKLevelSetsPython.py
itk/ITKMathematicalMorphologyPython.py
itk/ITKNarrowBandBasePython.py
itk/ITKNarrowBandPython.py
itk/ITKQuadEdgeMeshFilteringPython.py
itk/ITKSignedDistanceFunctionPython.py
itk/_ITKAnisotropicSmoothingPython.cpython-39-aarch64-linux-gnu.so
itk/_ITKAntiAliasPython.cpython-39-aarch64-linux-gnu.so
itk/_ITKBiasCorrectionPython.cpython-39-aarch64-linux-gnu.so
itk/_ITKBinaryMathematicalMorphologyPython.cpython-39-aarch64-linux-gnu.so
itk/_ITKColormapPython.cpython-39-aarch64-linux-gnu.so
itk/_ITKConnectedComponentsPython.cpython-39-aarch64-linux-gnu.so
itk/_ITKDeconvolutionPython.cpython-39-aarch64-linux-gnu.so
itk/_ITKDistanceMapPython.cpython-39-aarch64-linux-gnu.so
itk/_ITKFastMarchingPython.cpython-39-aarch64-linux-gnu.so
itk/_ITKImageComparePython.cpython-39-aarch64-linux-gnu.so
itk/_ITKImageFeaturePython.cpython-39-aarch64-linux-gnu.so
itk/_ITKImageFrequencyPython.cpython-39-aarch64-linux-gnu.so
itk/_ITKImageFusionPython.cpython-39-aarch64-linux-gnu.so
itk/_ITKImageGradientPython.cpython-39-aarch64-linux-gnu.so
itk/_ITKImageLabelPython.cpython-39-aarch64-linux-gnu.so
itk/_ITKImageNoisePython.cpython-39-aarch64-linux-gnu.so
itk/_ITKLabelMapPython.cpython-39-aarch64-linux-gnu.so
itk/_ITKLevelSetsPython.cpython-39-aarch64-linux-gnu.so
itk/_ITKMathematicalMorphologyPython.cpython-39-aarch64-linux-gnu.so
itk_filtering-5.4.4.post1.dist-info/METADATA
itk_filtering-5.4.4.post1.dist-info/WHEEL
itk_filtering-5.4.4.post1.dist-info/RECORD
itk_filtering-5.4.4.post1.dist-info/licenses/LICENSE
itk_filtering-5.4.4.post1.dist-info/licenses/ITK-source/ITK/LICENSE
itk_filtering-5.4.4.post1.dist-info/licenses/ITK-source/ITK/NOTICE
